WeatherNWS/SAME.json
WeatherNWS/__init__.py
WeatherNWS/api.py
WeatherNWS/counties.json
WeatherNWS/zone.json
WeatherNWS-0.0.7.dist-info/LICENCE.txt
WeatherNWS-0.0.7.dist-info/METADATA
WeatherNWS-0.0.7.dist-info/WHEEL
WeatherNWS-0.0.7.dist-info/top_level.txt
WeatherNWS-0.0.7.dist-info/RECORD
