Metadata-Version: 2.1
Name: WeatherNWS
Version: 0.0.7
Summary: Weather Functions and Data From NWS
Home-page: https://github.com/MatthewIsHere/WeatherNWS
Author: Matthew Lyon
Author-email: matthew@matthewlyon.net
License: UNKNOWN
Platform: UNKNOWN
Classifier: Programming Language :: Python :: 3
Classifier: License :: OSI Approved :: MIT License
Classifier: Operating System :: OS Independent
Requires-Python: >=3.6
